{"cameraMode":{"drawMode":0,"name":"Shaded","section":"Shading Mode"},"sceneLighting":true,"audioPlay":false,"sceneViewState":{"m_AlwaysRefresh":false,"showFog":true,"showSkybox":true,"showFlares":true,"showImageEffects":true,"showParticleSystems":true,"showVisualEffectGraphs":true,"m_FxEnabled":true},"in2DMode":false,"pivot":{"x":37.07776641845703,"y":18.2713623046875,"z":-7.867838382720947},"rotation":{"x":0.04712072014808655,"y":0.7584467530250549,"z":0.05515328422188759,"w":-0.6477393507957459},"size":10.449999809265137,"orthographic":false}